{
  "fetched_at": "2026-06-11T11:26:35.103632Z",
  "source": "Tarrant County Clerk \u2013 tarrant.tx.publicsearch.us",
  "date_range": "2026-06-04 to 2026-06-11",
  "total": 2,
  "with_address": 0,
  "records": [
    {
      "doc_num": "D226108513",
      "doc_type": "JUDGMENT",
      "filed": "2026-06-04",
      "cat": "JUD",
      "cat_label": "Judgment",
      "owner": "WELLS FARGO BANK",
      "grantee": "FORD ISHA T",
      "amount": 0.0,
      "legal": "",
      "clerk_url": "https://tarrant.tx.publicsearch.us/doc/D226108513",
      "prop_address": "",
      "prop_city": "Fort Worth",
      "prop_state": "TX",
      "prop_zip": "",
      "mail_address": "",
      "mail_city": "",
      "mail_state": "TX",
      "mail_zip": "",
      "flags": [
        "Judgment lien",
        "New this week"
      ],
      "score": 45,
      "person_name": "FORD ISHA T"
    },
    {
      "doc_num": "D226108261",
      "doc_type": "LIEN",
      "filed": "2026-06-04",
      "cat": "LN",
      "cat_label": "Lien",
      "owner": "TEXAS HEALTH FORT WORTH HOSPITAL",
      "grantee": "JACKMAN BRADLEY",
      "amount": 0.0,
      "legal": "",
      "clerk_url": "https://tarrant.tx.publicsearch.us/doc/D226108261",
      "prop_address": "",
      "prop_city": "Fort Worth",
      "prop_state": "TX",
      "prop_zip": "",
      "mail_address": "",
      "mail_city": "",
      "mail_state": "TX",
      "mail_zip": "",
      "flags": [
        "Lien",
        "New this week"
      ],
      "score": 45
    }
  ]
}